qrcode/LUT.py
qrcode/__init__.py
qrcode/base.py
qrcode/console_scripts.py
qrcode/constants.py
qrcode/exceptions.py
qrcode/main.py
qrcode/release.py
qrcode/util.py
qrcode/compat/__init__.py
qrcode/compat/etree.py
qrcode/compat/pil.py
qrcode/image/__init__.py
qrcode/image/base.py
qrcode/image/pil.py
qrcode/image/pure.py
qrcode/image/styledpil.py
qrcode/image/svg.py
qrcode/image/styles/__init__.py
qrcode/image/styles/colormasks.py
qrcode/image/styles/moduledrawers/__init__.py
qrcode/image/styles/moduledrawers/base.py
qrcode/image/styles/moduledrawers/pil.py
qrcode/image/styles/moduledrawers/svg.py
qrcode/tests/__init__.py
qrcode/tests/test_example.py
qrcode/tests/test_qrcode.py
qrcode/tests/test_qrcode_svg.py
qrcode/tests/test_release.py
qrcode/tests/test_script.py
qrcode/tests/test_util.py
qrcode-7.4.1.data/data/share/man/man1/qr.1
qrcode-7.4.1.dist-info/LICENSE
qrcode-7.4.1.dist-info/METADATA
qrcode-7.4.1.dist-info/WHEEL
qrcode-7.4.1.dist-info/entry_points.txt
qrcode-7.4.1.dist-info/top_level.txt
qrcode-7.4.1.dist-info/RECORD
