Metadata-Version: 2.1
Name: qrcode
Version: 7.4.1
Summary: QR Code image generator
Home-page: https://github.com/lincolnloop/python-qrcode
Author: Lincoln Loop
Author-email: info@lincolnloop.com
License: BSD
Keywords: qr denso-wave IEC18004
Classifier: Development Status :: 5 - Production/Stable
Classifier: License :: OSI Approved :: BSD License
Classifier: Operating System :: OS Independent
Classifier: Intended Audience :: Developers
Classifier: Programming Language :: Python
Classifier: Programming Language :: Python :: 3
Classifier: Programming Language :: Python :: 3.7
Classifier: Programming Language :: Python :: 3.8
Classifier: Programming Language :: Python :: 3.9
Classifier: Programming Language :: Python :: 3.10
Classifier: Programming Language :: Python :: 3 :: Only
Classifier: Topic :: Multimedia :: Graphics
Classifier: Topic :: Software Development :: Libraries :: Python Modules
Requires-Python: >=3.7
Provides-Extra: maintainer
Provides-Extra: dev
Provides-Extra: test
Provides-Extra: pil
Provides-Extra: all
License-File: LICENSE
